score_loader/__init__.py
score_loader/loader.py
score_loader/types.py
score_loader-0.0.4.dist-info/licenses/LICENSE
score_loader-0.0.4.dist-info/METADATA
score_loader-0.0.4.dist-info/WHEEL
score_loader-0.0.4.dist-info/top_level.txt
score_loader-0.0.4.dist-info/RECORD
