Metadata-Version: 2.4
Name: score_loader
Version: 0.0.4
Summary: Python implementation of the score.dev specification, allowing to load workload definition and applying a first pass of evaluation for ${metadata...} placeholders.
Project-URL: Repository, https://github.com/stumpyfr/score-loader
Project-URL: Documentation, https://github.com/stumpyfr/score-loader
Keywords: score.dev
Requires-Python: >=3.12
License-File: LICENSE
Requires-Dist: pydantic>=2.12.3
Requires-Dist: pyyaml>=6.0.3
Dynamic: license-file
